PhodalSIdeaShizhanZhinan/README.md
PhodalSIdeaShizhanZhinan/__init__.py
PhodalSIdeaShizhanZhinan/__main__.py
PhodalSIdeaShizhanZhinan/file.epub
PhodalSIdeaShizhanZhinan/index.html
PhodalSIdeaShizhanZhinan/css/__init__.py
PhodalSIdeaShizhanZhinan/css/annotations.css
PhodalSIdeaShizhanZhinan/css/main.css
PhodalSIdeaShizhanZhinan/css/normalize.css
PhodalSIdeaShizhanZhinan/css/popup.css
PhodalSIdeaShizhanZhinan/font/__init__.py
PhodalSIdeaShizhanZhinan/font/fontello.eot
PhodalSIdeaShizhanZhinan/font/fontello.svg
PhodalSIdeaShizhanZhinan/font/fontello.ttf
PhodalSIdeaShizhanZhinan/font/fontello.woff
PhodalSIdeaShizhanZhinan/img/__init__.py
PhodalSIdeaShizhanZhinan/img/annotator-glyph-sprite.png
PhodalSIdeaShizhanZhinan/img/annotator-icon-sprite.png
PhodalSIdeaShizhanZhinan/img/apple-touch-icon.png
PhodalSIdeaShizhanZhinan/img/cancelfullscreen.png
PhodalSIdeaShizhanZhinan/img/close.png
PhodalSIdeaShizhanZhinan/img/fullscreen.png
PhodalSIdeaShizhanZhinan/img/loader.gif
PhodalSIdeaShizhanZhinan/img/menu-icon.png
PhodalSIdeaShizhanZhinan/img/save.png
PhodalSIdeaShizhanZhinan/img/saved.png
PhodalSIdeaShizhanZhinan/img/settings-s.png
PhodalSIdeaShizhanZhinan/img/settings.png
PhodalSIdeaShizhanZhinan/img/star.png
PhodalSIdeaShizhanZhinan/js/__init__.py
PhodalSIdeaShizhanZhinan/js/epub.js
PhodalSIdeaShizhanZhinan/js/epub.min.js
PhodalSIdeaShizhanZhinan/js/epub.min.map
PhodalSIdeaShizhanZhinan/js/hooks.min.js
PhodalSIdeaShizhanZhinan/js/hooks.min.map
PhodalSIdeaShizhanZhinan/js/reader.js
PhodalSIdeaShizhanZhinan/js/reader.js.map
PhodalSIdeaShizhanZhinan/js/reader.min.js
PhodalSIdeaShizhanZhinan/js/reader.min.map
PhodalSIdeaShizhanZhinan/js/hooks/__init__.py
PhodalSIdeaShizhanZhinan/js/hooks/extensions/__init__.py
PhodalSIdeaShizhanZhinan/js/hooks/extensions/highlight.js
PhodalSIdeaShizhanZhinan/js/libs/__init__.py
PhodalSIdeaShizhanZhinan/js/libs/jquery.min.js
PhodalSIdeaShizhanZhinan/js/libs/localforage.min.js
PhodalSIdeaShizhanZhinan/js/libs/screenfull.js
phodal_s_idea_shizhan_zhinan-2024.3.1.0.dist-info/METADATA
phodal_s_idea_shizhan_zhinan-2024.3.1.0.dist-info/WHEEL
phodal_s_idea_shizhan_zhinan-2024.3.1.0.dist-info/entry_points.txt
phodal_s_idea_shizhan_zhinan-2024.3.1.0.dist-info/top_level.txt
phodal_s_idea_shizhan_zhinan-2024.3.1.0.dist-info/RECORD
